README.md
setup.py
smartninja_redis/__init__.py
smartninja_redis/client.py
smartninja_redis.egg-info/PKG-INFO
smartninja_redis.egg-info/SOURCES.txt
smartninja_redis.egg-info/dependency_links.txt
smartninja_redis.egg-info/requires.txt
smartninja_redis.egg-info/top_level.txt