Metadata-Version: 2.1
Name: smartninja-redis
Version: 0.2
Summary: SmartNinja Redis - a wrapper that simulates Redis on localhost and uses real Redis in production.
Home-page: https://github.com/smartninja/smartninja-redis
Author: Matej Ramuta
Author-email: matej.ramuta@gmail.com
License: MIT
Platform: UNKNOWN
Classifier: Programming Language :: Python :: 3
Classifier: License :: OSI Approved :: MIT License
Classifier: Operating System :: OS Independent
